l8qa/__init__.py
l8qa/cli.py
l8qa/qa.py
l8qa/qa_pre.py
rio_l8qa-0.1.1.dist-info/DESCRIPTION.rst
rio_l8qa-0.1.1.dist-info/METADATA
rio_l8qa-0.1.1.dist-info/RECORD
rio_l8qa-0.1.1.dist-info/WHEEL
rio_l8qa-0.1.1.dist-info/entry_points.txt
rio_l8qa-0.1.1.dist-info/metadata.json
rio_l8qa-0.1.1.dist-info/top_level.txt
