Metadata-Version: 2.0
Name: rio-l8qa
Version: 0.1.1
Summary: CLI and python module for working with Landsat 8 QA band
Home-page: https://github.com/mapbox/rio-l8qa
Author: Matthew Perry
Author-email: perry@mapbox.com
License: BSD
Platform: UNKNOWN
Requires-Dist: click
Requires-Dist: rasterio (>=0.36)
Provides-Extra: test
Requires-Dist: coveralls; extra == 'test'
Requires-Dist: pytest; extra == 'test'
Requires-Dist: pytest-cov; extra == 'test'
